vsrs/__init__.py
vsrs/__main__.py
vsrs/_version.py
vsrs/dims.py
vsrs/paster.py
vsrs/rescale.py
vsrs-0.1.0.dist-info/licenses/LICENSE.txt
vsrs-0.1.0.dist-info/METADATA
vsrs-0.1.0.dist-info/WHEEL
vsrs-0.1.0.dist-info/entry_points.txt
vsrs-0.1.0.dist-info/top_level.txt
vsrs-0.1.0.dist-info/RECORD
